{
  "type": "Feature",
  "properties": {
    "gn:admin1_code":"00",
    "gn:asciiname":"Lai Chi Van",
    "gn:country_code":"MO",
    "gn:dem":22,
    "gn:feature_class":"P",
    "gn:feature_code":"PPL",
    "gn:name":"Lai Chi Van",
    "gn:population":0,
    "gn:timezone":"Asia/Macau",
    "iso:country":"MO",
    "name:por_x_preferred":[
        "Povoa\u00e7\u00e3o de Lai Chi Van"
    ],
    "name:und_x_variant":[
        "Lui-Tchi-Van",
        "Lizhiwan",
        "Lai Chi Van"
    ],
    "name:zho_x_preferred":[
        "\u8354\u679d\u7897"
    ],
    "wof:name":"Lai Chi Van",
    "wof:placetype":"locality"
},
  "geometry": {"coordinates":[113.55110999999999,22.11972],"type":"Point"}
}